Metadata-Version: 1.0
Name: depopwatch
Version: 0.1.1
Summary: A very simple module to watch Depop accounts for new listings
Home-page: http://github.com/WilliamWCYoung/depopwatch
Author: William Young
Author-email: william.w.c.young@hotmail.com
License: MIT
Platform: UNKNOWN
